[
  {
    "line_id": "prizepicks_3304884",
    "game_id": "2024-11-10_edmonton-oilers_vancouver-canucks",
    "players": [
      {
        "normalized_name": "conor garland",
        "name": "Conor Garland",
        "team": "vancouver canucks"
      }
    ],
    "line": 0.5,
    "market": "points",
    "league": "NHL",
    "is_available": false,
    "sportsbook": "PrizePicks",
    "game_date": "2024-11-10",
    "start_time": "2024-11-10T03:00:00.000Z",
    "grade": "not-started",
    "line_changes": [
      {
        "timestamp": "2024-11-09T15:47:26.575Z",
        "value": 0.5
      }
    ]
  },
  {
    "line_id": "prizepicks_3304883",
    "game_id": "2024-11-10_edmonton-oilers_vancouver-canucks",
    "players": [
      {
        "normalized_name": "connor mcdavid",
        "name": "Connor McDavid",
        "team": "edmonton oilers"
      }
    ],
    "line": 1.5,
    "market": "points",
    "league": "NHL",
    "is_available": false,
    "sportsbook": "PrizePicks",
    "game_date": "2024-11-10",
    "start_time": "2024-11-10T03:00:00.000Z",
    "grade": "not-started",
    "line_changes": [
      {
        "timestamp": "2024-11-09T15:47:26.575Z",
        "value": 1.5
      }
    ]
  },
  {
    "line_id": "prizepicks_3303827",
    "game_id": "2024-11-10_edmonton-oilers_vancouver-canucks",
    "players": [
      {
        "normalized_name": "jeff skinner",
        "name": "Jeff Skinner",
        "team": "edmonton oilers"
      }
    ],
    "line": 2.5,
    "market": "shots on goal",
    "league": "NHL",
    "is_available": false,
    "sportsbook": "PrizePicks",
    "game_date": "2024-11-10",
    "start_time": "2024-11-10T03:00:00.000Z",
    "grade": "not-started",
    "line_changes": [
      {
        "timestamp": "2024-11-09T08:17:26.408Z",
        "value": 2.5
      }
    ]
  },
  {
    "line_id": "prizepicks_3303824",
    "game_id": "2024-11-10_edmonton-oilers_vancouver-canucks",
    "players": [
      {
        "normalized_name": "quinn hughes",
        "name": "Quinn Hughes",
        "team": "vancouver canucks"
      }
    ],
    "line": 2.5,
    "market": "shots on goal",
    "league": "NHL",
    "is_available": false,
    "sportsbook": "PrizePicks",
    "game_date": "2024-11-10",
    "start_time": "2024-11-10T03:00:00.000Z",
    "grade": "not-started",
    "line_changes": [
      {
        "timestamp": "2024-11-09T08:17:26.408Z",
        "value": 2.5
      }
    ]
  },
  {
    "line_id": "prizepicks_3304881",
    "game_id": "2024-11-10_columbus-blue-jackets_los-angeles-kings",
    "players": [
      {
        "normalized_name": "alex laferriere",
        "name": "Alex Laferriere",
        "team": "los angeles kings"
      }
    ],
    "line": 0.5,
    "market": "points",
    "league": "NHL",
    "is_available": false,
    "sportsbook": "PrizePicks",
    "game_date": "2024-11-10",
    "start_time": "2024-11-10T02:00:00.000Z",
    "grade": "not-started",
    "line_changes": [
      {
        "timestamp": "2024-11-09T15:47:26.575Z",
        "value": 0.5
      }
    ]
  },
  {
    "line_id": "prizepicks_3303863",
    "game_id": "2024-11-10_carolina-hurricanes_colorado-avalanche",
    "players": [
      {
        "normalized_name": "martin necas",
        "name": "Martin Necas",
        "team": "carolina hurricanes"
      }
    ],
    "line": 0.5,
    "market": "assists",
    "league": "NHL",
    "is_available": false,
    "sportsbook": "PrizePicks",
    "game_date": "2024-11-10",
    "start_time": "2024-11-10T02:00:00.000Z",
    "grade": "not-started",
    "line_changes": [
      {
        "timestamp": "2024-11-09T09:37:26.401Z",
        "value": 0.5
      }
    ]
  },
  {
    "line_id": "prizepicks_3303857",
    "game_id": "2024-11-10_columbus-blue-jackets_los-angeles-kings",
    "players": [
      {
        "normalized_name": "alex laferriere",
        "name": "Alex Laferriere",
        "team": "los angeles kings"
      }
    ],
    "line": 0.5,
    "market": "points",
    "league": "NHL",
    "is_available": false,
    "sportsbook": "PrizePicks",
    "game_date": "2024-11-10",
    "start_time": "2024-11-10T02:00:00.000Z",
    "grade": "not-started",
    "line_changes": [
      {
        "timestamp": "2024-11-09T08:54:26.381Z",
        "value": 0.5
      }
    ]
  }
]